[{"model": "products.category", "pk": 1, "fields": {"name": "activewear", "friendly_name": "Activewear"}}, {"model": "products.category", "pk": 2, "fields": {"name": "gear", "friendly_name": "Gear"}}, {"model": "products.category", "pk": 3, "fields": {"name": "health_products", "friendly_name": "Health Products"}}, {"model": "products.category", "pk": 4, "fields": {"name": "subscription", "friendly_name": "Subscription"}}, {"model": "products.category", "pk": 5, "fields": {"name": "personal_training", "friendly_name": "Personal Training"}}]